LICENSE
README.md
pyproject.toml
setup.py
ungi_utils/Config.py
ungi_utils/Elastic_Wrapper.py
ungi_utils/File_utils.py
ungi_utils/Sqlite3_Utils.py
ungi_utils/__init__.py
ungi_utils/logging.py
ungi_utils/logging_utils.py
ungi_utils/utils.py
ungi_utils.egg-info/PKG-INFO
ungi_utils.egg-info/SOURCES.txt
ungi_utils.egg-info/dependency_links.txt
ungi_utils.egg-info/requires.txt
ungi_utils.egg-info/top_level.txt