Metadata-Version: 1.0
Name: ungi-utils
Version: 0.1.13
Summary: Utils needed for the UNGI project
Home-page: UNKNOWN
Author: Unseen Giants
Author-email: incoming+unseen-giants-ungi-utils-26498131-issue-@incoming.gitlab.com
License: GPL 3.0
Platform: UNKNOWN
